samosila/__init__.py
samosila/core/__init__.py
samosila/core/integrations/__init__.py
samosila/core/integrations/callbacks/__init__.py
samosila/core/integrations/callbacks/aim.py
samosila/core/integrations/callbacks/confident.py
samosila/core/integrations/callbacks/context.py
samosila/core/integrations/callbacks/launry.py
samosila/core/integrations/callbacks/prompt_layer.py
samosila/core/integrations/callbacks/streaming_stdout.py
samosila/core/integrations/manipulations/__init__.py
samosila/core/integrations/manipulations/cache.py
samosila/core/integrations/manipulations/cost.py
samosila/core/integrations/manipulations/function_call.py
samosila/core/integrations/manipulations/prompt.py
samosila/core/integrations/manipulations/tools_call.py
samosila/core/integrations/manipulations/user.py
samosila/core/providers/__init__.py
samosila/core/providers/cohere.py
samosila/core/providers/ctranslate.py
samosila/core/providers/eleven_labs.py
samosila/core/providers/fake.py
samosila/core/providers/faster_whisper.py
samosila/core/providers/fireworks.py
samosila/core/providers/genai.py
samosila/core/providers/gf4.py
samosila/core/providers/gradient.py
samosila/core/providers/huggingface.py
samosila/core/providers/llama_cpp.py
samosila/core/providers/novita.py
samosila/core/providers/openai.py
samosila/core/providers/segmind.py
samosila/core/providers/together.py
samosila/core/providers/tts.py
samosila/core/providers/voyage.py
samosila/core/types/__init__.py
samosila/core/types/callbacks.py
samosila/core/types/errors.py
samosila/core/types/manipulations.py
samosila/core/types/message_history.py
samosila/core/types/prompt.py
samosila/core/types/prompts.py
samosila/core/types/provider_base.py
samosila/core/types/provider_inputs.py
samosila/core/types/response_types.py
samosila/core/types/states.py
samosila/core/types/utils.py
samosila/core/utils/__init__.py
samosila/core/utils/cost.py
samosila/core/utils/image.py
samosila/core/utils/json.py
samosila/core/utils/text_splitter.py
samosila_core-0.0.7.dist-info/METADATA
samosila_core-0.0.7.dist-info/WHEEL
samosila_core-0.0.7.dist-info/top_level.txt
samosila_core-0.0.7.dist-info/RECORD
